Memory.v
module Memory(CS, WE, CLK, ADDR, Mem_Bus);
    
    input CS, WE, CLK;
    input [31:0] ADDR;
    inout [31:0] Mem_Bus;
    reg [31:0] data_out;
    reg [31:0] RAM [0:127];
    integer i;
    reg[6:0] counter;
    initial begin
        for (i=0; i<128; i=i+1)
        begin
            RAM[i] = 32'd0; //initialize all locations to 0
        end
        $readmemh("MIPS_Instructions.txt", RAM);
        // this optional statement can be inserted to read initial values
        // from a file
    end

    assign Mem_Bus = ((CS == 1'b0) || (WE == 1'b1)) ? 32'bZ : data_out;
    always @(negedge CLK) begin
        if((CS == 1'b1) && (WE == 1'b1))
        RAM[ADDR] <= Mem_Bus[31:0];
        data_out <= RAM[ADDR];
    end

endmodule

Register.v
module Register(CLK, RegW, DR, SR1, SR2, Reg_In, ReadReg1, ReadReg2);
    
    input CLK, RegW;
    input [4:0] DR, SR1, SR2;
    input [31:0] Reg_In;
    output reg [31:0] ReadReg1, ReadReg2;
    reg [31:0] REG [0:31];
    integer i;
    initial begin
        ReadReg1 = 0;
        ReadReg2 = 0;
        for (i = 0; i < 32; i = i+1) begin
            REG[i] = 0;
        end
    end
    always @(posedge CLK) begin
        if(RegW == 1'b1)
        REG[DR] <= Reg_In[31:0];
        ReadReg1 <= REG[SR1];
        ReadReg2 <= REG[SR2];
    end

endmodule

MIPS.v
// MIPS Subset implementation

`define opcode instr[31:26]
`define sr1 instr[25:21]
`define sr2 instr[20:16]
`define f_code instr[5:0]
`define numshift instr[10:6]

module MIPS (CLK, RST, CS, WE, ADDR, Mem_Bus);
    
    input CLK, RST;
    output reg CS, WE;
    output [31:0] ADDR;
    inout [31:0] Mem_Bus;
    // special instructions (opcode == 000000), values of F code (bits 5-0):
    parameter add = 6'b100000;
    parameter sub = 6'b100010;
    parameter xor1 = 6'b100110;
    parameter and1 = 6'b100100;
    parameter or1 = 6'b100101;
    parameter slt = 6'b101010;
    parameter srl = 6'b000010;
    parameter sll = 6'b000000;
    parameter jr = 6'b001000;
    // non-special instructions, values of opcodes:
    parameter addi = 6'b001000;
    parameter andi = 6'b001100;
    parameter ori = 6'b001101;
    parameter lw = 6'b100011;
    parameter sw = 6'b101011;
    parameter beq = 6'b000100;
    parameter bne = 6'b000101;
    parameter j = 6'b000010;
    // instruction format
    parameter R = 2'd0;
    parameter I = 2'd1;
    parameter J = 2'd2;
    // internal signals
    reg [5:0] op, opsave;
    wire [1:0] format;
    reg [31:0] instr, pc, npc, alu_result;
    wire [31:0] imm_ext, alu_in_A, alu_in_B, reg_in, readreg1, readreg2;
    reg [31:0] alu_result_save;
    reg alu_or_mem, alu_or_mem_save, regw, writing, reg_or_imm,
    reg_or_imm_save;
    reg fetchDorI;
    wire [4:0] dr;
    reg [2:0] state, nstate;
    // combinational
    assign imm_ext = (instr[15] == 1)? {16'hFFFF, instr[15:0]} : {16'h0000,
    instr[15:0]};// sign extend immediate field
    assign dr = (format == R)? instr[15:11] : instr[20:16];
    // destination Register MUX (MUX1)
    assign alu_in_A = readreg1;
    assign alu_in_B = (reg_or_imm_save)? imm_ext : readreg2;
    // ALU MUX (MUX2)
    assign reg_in = (alu_or_mem_save)? Mem_Bus : alu_result_save;
    // Data MUX
    assign format = (`opcode == 6'd0)? R : ((`opcode == 6'd2)? J : I);
    assign Mem_Bus = (writing)? readreg2 : 32'bZZZZZZZZZZZZZZZZZZZZZZZZZZZZZZZZ;
    // drive memory bus only during writes
    assign ADDR = (fetchDorI)? pc : alu_result_save;
    // ADDR Mux
    Register REG(CLK, regw, dr, `sr1, `sr2, reg_in, readreg1, readreg2);
    initial begin
        op = and1;
        opsave = and1;
        state = 3'b0;
        nstate = 3'b0;
        alu_or_mem = 0;
        regw = 0;
        fetchDorI = 0;
        writing = 0;
        reg_or_imm = 0;
        reg_or_imm_save = 0;
        alu_or_mem_save = 0;
    end
    
    always @(*)
    begin
        fetchDorI = 0; CS = 0; WE = 0; regw = 0; writing = 0; alu_result = 32'd0;
        npc = pc; op = jr; reg_or_imm = 0; alu_or_mem = 0;
        case (state)
            0:  begin // fetch
                    npc = pc + 32'd1; CS = 1; nstate = 3'd1;
                    fetchDorI = 1;
                end
            1:  begin // decode
                    nstate = 3'd2; reg_or_imm = 0; alu_or_mem = 0;
                    if (format == J) begin //jump, and finish
                    npc = {pc[31:26], instr[25:0]};
                    nstate = 3'd0;
                end
                else if (format == R) // register instructions
                    op = `f_code;
                else if (format == I) begin // immediate instructions
                    reg_or_imm = 1;
                    if(`opcode == lw) begin
                        op = add;
                        alu_or_mem = 1;
                    end
                    else if ((`opcode == lw)||(`opcode == sw)||(`opcode == addi))
                        op = add;
                    else if ((`opcode == beq)||(`opcode == bne)) begin
                        op = sub;
                        reg_or_imm = 0;
                    end
                    else if (`opcode == andi) op = and1;
                    else if (`opcode == ori) op = or1;
                end
            end

            2: begin // execute
                nstate = 3'd3;
                if (opsave == and1) alu_result = alu_in_A & alu_in_B;
                else if (opsave == or1) alu_result = alu_in_A | alu_in_B;
                else if (opsave == add) alu_result = alu_in_A + alu_in_B;
                else if (opsave == sub) alu_result = alu_in_A - alu_in_B;
                else if (opsave == srl) alu_result = alu_in_B >> `numshift;
                else if (opsave == sll) alu_result = alu_in_B << `numshift;
                else if (opsave == slt) alu_result = (alu_in_A < alu_in_B)? 32'd1 :
                32'd0;
                else if (opsave == xor1) alu_result = alu_in_A ^ alu_in_B;
                if (((alu_in_A == alu_in_B)&&(`opcode == beq)) || ((alu_in_A != alu_in_B)&&(`opcode == bne))) begin
                    npc = pc + imm_ext;
                    nstate = 3'd0;
                end
                else if ((`opcode == bne)||(`opcode == beq)) nstate = 3'd0;
                else if (opsave == jr) begin
                    npc = alu_in_A;
                    nstate = 3'd0;
                end
            end

            3: begin //prepare to write to mem
                nstate = 3'd0;
                if ((format == R)||(`opcode == addi)||(`opcode == andi)||(`opcode == ori))
                    regw = 1;
                else if (`opcode == sw) begin
                    CS = 1;
                    WE = 1;
                    writing = 1;
                end
                else if (`opcode == lw) begin
                    CS = 1;
                    nstate = 3'd4;
                end
            end

            4: begin
                nstate = 3'd0;
                CS = 1;
                if (`opcode == lw) regw = 1;
            end
        endcase
    end // always
    
    always @(posedge CLK) begin
        if (RST) begin
            state <= 3'd0;
            pc <= 32'd0;
        end
        else begin
            state <= nstate;
            pc <= npc;
        end
        if (state == 3'd0) instr <= Mem_Bus;
        else if (state == 3'd1) begin
            opsave <= op;
            reg_or_imm_save <= reg_or_imm;
            alu_or_mem_save <= alu_or_mem;
        end
        else if (state == 3'd2) alu_result_save <= alu_result;
    end // always
endmodule

mips_testbench.v
module mips_testbench;
    reg CLK;
    wire CS, WE;

    parameter N = 10;
    reg[31:0] expected[N:1];

    wire[31:0] Address, Address_Mux, Mem_Bus_Wire;
    reg[31:0] AddressTB;
    wire WE_Mux, CS_Mux;
    reg init, rst, WE_TB, CS_TB;

    integer i;

    MIPS CPU(CLK, rst, CS, WE, Address, Mem_Bus_Wire);
    Memory MEM(CS_Mux, WE_Mux, CLK, Address_Mux, Mem_Bus_Wire);

    assign Address_Mux = (init)? AddressTB : Address;
    assign WE_Mux = (init)? WE_TB : WE;
    assign CS_Mux = (init)? CS_TB : CS;

    always
    #10 CLK = ~CLK;

    initial begin
        $dumpfile("mips.vcd");
        $dumpvars(0,mips_testbench);

        expected[1] = 32'h00000006; // $1 content=6 decimal
        expected[2] = 32'h00000012; // $2 content=18 decimal
        expected[3] = 32'h00000018; // $3 content=24 decimal
        expected[4] = 32'h0000000C; // $4 content=12 decimal
        expected[5] = 32'h00000002; // $5 content=2
        expected[6] = 32'h00000016; // $6 content=22 decimal
        expected[7] = 32'h00000001; // $7 content=1
        expected[8] = 32'h00000120; // $8 content=288 decimal
        expected[9] = 32'h00000003; // $9 content=3
        expected[10] = 32'h00412022; // $10 content=5th instr
        CLK = 0;
    end

    always begin
        rst = 1;
        @(posedge CLK); // wait until posedge CLK
        //Initialize the instructions from the testbench
            init <= 1; CS_TB <= 1; WE_TB <= 1;
        @(posedge CLK);
            CS_TB <= 0; WE_TB <= 0; init <= 0;
        @(posedge CLK);
            rst <= 0;
        
        for(i = 1; i <= N; i = i+1) begin
            @(posedge WE); // When a store word is executed
            @(negedge CLK);
            if (Mem_Bus_Wire != expected[i])
            $display("Output mismatch: got %d, expect %d", Mem_Bus_Wire,
                        expected[i]);
        end
        $display("Testing Finished:");
        $finish;
    end

endmodule

mips.vcd
$date
	Sat Feb 15 18:32:18 2025
$end
$version
	Icarus Verilog
$end
$timescale
	1s
$end
$scope module mips_testbench $end
$var wire 32 ! Mem_Bus_Wire [31:0] $end
$var wire 1 " WE_Mux $end
$var wire 1 # WE $end
$var wire 1 $ CS_Mux $end
$var wire 1 % CS $end
$var wire 32 & Address_Mux [31:0] $end
$var wire 32 ' Address [31:0] $end
$var reg 32 ( AddressTB [31:0] $end
$var reg 1 ) CLK $end
$var reg 1 * CS_TB $end
$var reg 1 + WE_TB $end
$var reg 1 , init $end
$var reg 1 - rst $end
$var integer 32 . i [31:0] $end
$scope module CPU $end
$var wire 1 ) CLK $end
$var wire 32 / Mem_Bus [31:0] $end
$var wire 1 - RST $end
$var wire 32 0 alu_in_A [31:0] $end
$var wire 32 1 reg_in [31:0] $end
$var wire 32 2 readreg2 [31:0] $end
$var wire 32 3 readreg1 [31:0] $end
$var wire 32 4 imm_ext [31:0] $end
$var wire 2 5 format [1:0] $end
$var wire 5 6 dr [4:0] $end
$var wire 32 7 alu_in_B [31:0] $end
$var wire 32 8 ADDR [31:0] $end
$var reg 1 % CS $end
$var reg 1 # WE $end
$var reg 1 9 alu_or_mem $end
$var reg 1 : alu_or_mem_save $end
$var reg 32 ; alu_result [31:0] $end
$var reg 32 < alu_result_save [31:0] $end
$var reg 1 = fetchDorI $end
$var reg 32 > instr [31:0] $end
$var reg 32 ? npc [31:0] $end
$var reg 3 @ nstate [2:0] $end
$var reg 6 A op [5:0] $end
$var reg 6 B opsave [5:0] $end
$var reg 32 C pc [31:0] $end
$var reg 1 D reg_or_imm $end
$var reg 1 E reg_or_imm_save $end
$var reg 1 F regw $end
$var reg 3 G state [2:0] $end
$var reg 1 H writing $end
$scope module REG $end
$var wire 1 ) CLK $end
$var wire 5 I DR [4:0] $end
$var wire 1 F RegW $end
$var wire 32 J Reg_In [31:0] $end
$var wire 5 K SR1 [4:0] $end
$var wire 5 L SR2 [4:0] $end
$var reg 32 M ReadReg1 [31:0] $end
$var reg 32 N ReadReg2 [31:0] $end
$var integer 32 O i [31:0] $end
$upscope $end
$upscope $end
$scope module MEM $end
$var wire 32 P ADDR [31:0] $end
$var wire 1 ) CLK $end
$var wire 1 $ CS $end
$var wire 32 Q Mem_Bus [31:0] $end
$var wire 1 " WE $end
$var reg 32 R data_out [31:0] $end
$var integer 32 S i [31:0] $end
$upscope $end
$upscope $end
$enddefinitions $end
#0
$dumpvars
b10000000 S
bx R
bx Q
bx P
b100000 O
b0 N
b0 M
bx L
bx K
bx J
bx I
0H
b0 G
0F
0E
0D
bx C
b100100 B
b1000 A
b1 @
bx ?
bx >
1=
bx <
b0 ;
0:
09
bx 8
b0 7
bx 6
bx 5
bx 4
b0 3
b0 2
bx 1
b0 0
bx /
bx .
1-
x,
x+
x*
0)
bx (
bx '
bx &
1%
x$
0#
x"
bx !
$end
#10
bz !
bz /
bz Q
bx 7
b1 ?
1%
1=
b0 '
b0 8
1"
1$
bx 2
bx N
bx 0
bx 3
bx M
b0 C
1+
1*
1,
1)
#20
0)
#30
bx !
bx /
bx Q
bxzzzzzzzzzzzzzzzz 4
bz 6
bz I
b0 &
b0 P
0"
b1 ?
1%
1=
bz K
bz L
0,
0+
0*
bz >
1)
#40
b110000000000000000000000000000 !
b110000000000000000000000000000 /
b110000000000000000000000000000 Q
b110000000000000000000000000000 R
0)
#50
b0 4
b0 6
b0 I
b1 5
b1 ?
1%
1=
b0 K
b0 L
b110000000000000000000000000000 >
0-
b1 .
1)
#60
0)
#70
bz !
bz /
bz Q
bx &
bx P
0$
bx '
bx 8
b0 7
b100100 A
1D
b10 @
0%
0=
b1 C
b1 G
b0 2
b0 N
b0 0
b0 3
b0 M
1)
#80
bx R
0)
#90
b11 @
0D
b1000 A
1E
b10 G
1)
#100
0)
#110
b0 &
b0 P
b0 1
b0 J
b0 '
b0 8
1F
b0 @
b0 <
b11 G
1)
#120
b110000000000000000000000000000 R
0)
#130
b110000000000000000000000000000 !
b110000000000000000000000000000 /
b110000000000000000000000000000 Q
b1 &
b1 P
b1 '
b1 8
1$
1=
b1 @
1%
b10 ?
0F
b0 G
1)
#140
b100000000000010000000000000110 !
b100000000000010000000000000110 /
b100000000000010000000000000110 Q
b100000000000010000000000000110 R
0)
#150
bz !
bz /
bz Q
b110 7
b110 4
b1 6
b1 I
b0 &
b0 P
0$
b1 L
b0 '
b0 8
b100000 A
1D
b10 @
0%
0=
b100000000000010000000000000110 >
b10 C
b1 G
1)
#160
b110000000000000000000000000000 R
0)
#170
b110 ;
b11 @
0D
b1000 A
b100000 B
b10 G
1)
#180
0)
#190
b110 &
b110 P
b110 1
b110 J
b110 '
b110 8
1F
b0 @
b0 ;
b110 <
b11 G
1)
#200
b1000100011000000100101 R
0)
#210
b1000100011000000100101 !
b1000100011000000100101 /
b1000100011000000100101 Q
b10 &
b10 P
b10 '
b10 8
1$
1=
b1 @
1%
b11 ?
0F
b0 G
1)
#220
b110100000000100000000000010010 !
b110100000000100000000000010010 /
b110100000000100000000000010010 Q
b110100000000100000000000010010 R
0)
#230
bz !
bz /
bz Q
b10010 7
b10010 4
b10 6
b10 I
b110 &
b110 P
0$
b10 L
b110 '
b110 8
b100101 A
1D
b10 @
0%
0=
b110100000000100000000000010010 >
b11 C
b1 G
b110 2
b110 N
1)
#240
b1000100011000000100101 R
0)
#250
b10010 ;
b11 @
0D
b1000 A
b0 2
b0 N
b100101 B
b10 G
1)
#260
0)
#270
b10010 &
b10010 P
b10010 1
b10010 J
b10010 '
b10010 8
1F
b0 @
b0 ;
b10010 <
b11 G
1)
#280
b10101100000000010000000001000000 R
0)
#290
b10101100000000010000000001000000 !
b10101100000000010000000001000000 /
b10101100000000010000000001000000 Q
b11 &
b11 P
b11 '
b11 8
1$
1=
b1 @
1%
b100 ?
0F
b0 G
1)
#300
b1000100001100000100000 !
b1000100001100000100000 /
b1000100001100000100000 Q
b1000100001100000100000 R
0)
#310
bz !
bz /
bz Q
b1100000100000 7
b11 6
b11 I
b100000 A
b1100000100000 4
b0 5
b10010 &
b10010 P
0$
b1 K
b10010 '
b10010 8
0D
b10 @
0%
0=
b1000100001100000100000 >
b100 C
b1 G
b10010 2
b10010 N
1)
#320
b10101100000000010000000001000000 R
0)
#330
b10010 7
b11000 ;
b11 @
b1000 A
b110 0
b110 3
b110 M
0E
b100000 B
b10 G
1)
#340
0)
#350
b11000 &
b11000 P
b11000 1
b11000 J
b11000 '
b11000 8
1F
b0 @
b0 ;
b11000 <
b11 G
1)
#360
b10101100000001110000000001000110 R
0)
#370
b10101100000001110000000001000110 !
b10101100000001110000000001000110 /
b10101100000001110000000001000110 Q
b100 &
b100 P
b100 '
b100 8
1$
1=
b1 @
1%
b101 ?
0F
b0 G
1)
#380
b10000010010000000100010 !
b10000010010000000100010 /
b10000010010000000100010 Q
b10000010010000000100010 R
0)
#390
bz !
bz /
bz Q
b10000000100010 4
b100 6
b100 I
b11000 &
b11000 P
0$
b10 K
b1 L
b11000 '
b11000 8
b100010 A
b10 @
0%
0=
b10000010010000000100010 >
b101 C
b1 G
1)
#400
b10101100000001110000000001000110 R
0)
#410
b1100 ;
b110 7
b11 @
b1000 A
b110 2
b110 N
b10010 0
b10010 3
b10010 M
b100010 B
b10 G
1)
#420
0)
#430
b1100 &
b1100 P
b1100 1
b1100 J
b1100 '
b1100 8
1F
b0 @
b0 ;
b1100 <
b11 G
1)
#440
b10100011000100000000000000001 R
0)
#450
b10100011000100000000000000001 !
b10100011000100000000000000001 /
b10100011000100000000000000001 Q
b101 &
b101 P
b101 '
b101 8
1$
1=
b1 @
1%
b110 ?
0F
b0 G
1)
#460
b1000100010100000100100 !
b1000100010100000100100 /
b1000100010100000100100 Q
b1000100010100000100100 R
0)
#470
bz !
bz /
bz Q
b10100000100100 4
b101 6
b101 I
b1100 &
b1100 P
0$
b1 K
b10 L
b1100 '
b1100 8
b100100 A
b10 @
0%
0=
b1000100010100000100100 >
b110 C
b1 G
1)
#480
b10100011000100000000000000001 R
0)
#490
b10010 7
b10 ;
b11 @
b1000 A
b10010 2
b10010 N
b110 0
b110 3
b110 M
b100100 B
b10 G
1)
#500
0)
#510
b10 &
b10 P
b10 1
b10 J
b10 '
b10 8
1F
b0 @
b0 ;
b10 <
b11 G
1)
#520
b110100000000100000000000010010 R
0)
#530
b110100000000100000000000010010 !
b110100000000100000000000010010 /
b110100000000100000000000010010 Q
b110 &
b110 P
b110 '
b110 8
1$
1=
b1 @
1%
b111 ?
0F
b0 G
1)
#540
b1000100011000000100101 !
b1000100011000000100101 /
b1000100011000000100101 Q
b1000100011000000100101 R
0)
#550
bz !
bz /
bz Q
b11000000100101 4
b110 6
b110 I
b10 &
b10 P
0$
b10 '
b10 8
b100101 A
b10 @
0%
0=
b1000100011000000100101 >
b111 C
b1 G
1)
#560
b110100000000100000000000010010 R
0)
#570
b10110 ;
b11 @
b1000 A
b100101 B
b10 G
1)
#580
0)
#590
b10110 &
b10110 P
b10110 1
b10110 J
b10110 '
b10110 8
1F
b0 @
b0 ;
b10110 <
b11 G
1)
#600
b10101100000001010000000001000100 R
0)
#610
b10101100000001010000000001000100 !
b10101100000001010000000001000100 /
b10101100000001010000000001000100 Q
b111 &
b111 P
b111 '
b111 8
1$
1=
b1 @
1%
b1000 ?
0F
b0 G
1)
#620
b1000100011100000101010 !
b1000100011100000101010 /
b1000100011100000101010 Q
b1000100011100000101010 R
0)
#630
bz !
bz /
bz Q
b11100000101010 4
b111 6
b111 I
b10110 &
b10110 P
0$
b10110 '
b10110 8
b101010 A
b10 @
0%
0=
b1000100011100000101010 >
b1000 C
b1 G
1)
#640
b10101100000001010000000001000100 R
0)
#650
b1 ;
b11 @
b1000 A
b101010 B
b10 G
1)
#660
0)
#670
b1 &
b1 P
b1 1
b1 J
b1 '
b1 8
1F
b0 @
b0 ;
b1 <
b11 G
1)
#680
b100000000000010000000000000110 R
0)
#690
b100000000000010000000000000110 !
b100000000000010000000000000110 /
b100000000000010000000000000110 Q
b1000 &
b1000 P
b1000 '
b1000 8
1$
1=
b1 @
1%
b1001 ?
0F
b0 G
1)
#700
b100100000100000000 !
b100100000100000000 /
b100100000100000000 Q
b100100000100000000 R
0)
#710
bz !
bz /
bz Q
b100000100000000 4
b1000 6
b1000 I
b1 &
b1 P
0$
b0 K
b1 '
b1 8
b0 A
b10 @
0%
0=
b100100000100000000 >
b1001 C
b1 G
1)
#720
b100000000000010000000000000110 R
0)
#730
b100100000 ;
b11 @
b1000 A
b0 0
b0 3
b0 M
b0 B
b10 G
1)
#740
0)
#750
b100100000 &
b100100000 P
b100100000 1
b100100000 J
b100100000 '
b100100000 8
1F
b0 @
b0 ;
b100100000 <
b11 G
1)
#760
bx R
0)
#770
bx !
bx /
bx Q
b1001 &
b1001 P
b1001 '
b1001 8
1$
1=
b1 @
1%
b1010 ?
0F
b0 G
1)
#780
b10100100001000010 !
b10100100001000010 /
b10100100001000010 Q
b10100100001000010 R
0)
#790
bz !
bz /
bz Q
b100100001000010 4
b1001 6
b1001 I
b100100000 &
b100100000 P
0$
b1 L
b100100000 '
b100100000 8
b10 A
b10 @
0%
0=
b10100100001000010 >
b1010 C
b1 G
1)
#800
bx R
0)
#810
b110 7
b11 ;
b11 @
b1000 A
b110 2
b110 N
b10 B
b10 G
1)
#820
0)
#830
b11 &
b11 P
b11 1
b11 J
b11 '
b11 8
1F
b0 @
b0 ;
b11 <
b11 G
1)
#840
b1000100001100000100000 R
0)
#850
b1000100001100000100000 !
b1000100001100000100000 /
b1000100001100000100000 Q
b1010 &
b1010 P
b1010 '
b1010 8
1$
1=
b1 @
1%
b1011 ?
0F
b0 G
1)
#860
b10000001000100000000000000001 !
b10000001000100000000000000001 /
b10000001000100000000000000001 Q
b10000001000100000000000000001 R
0)
#870
bz !
bz /
bz Q
0D
b1 4
b10 6
b10 I
b1 5
b11 &
b11 P
0$
b1 K
b10 L
b11 '
b11 8
b100010 A
b10 @
0%
0=
b10000001000100000000000000001 >
b1011 C
b1 G
1)
#880
b1000100001100000100000 R
0)
#890
b11111111111111111111111111110100 ;
b10010 7
b1011 ?
b0 @
b1000 A
b10010 2
b10010 N
b110 0
b110 3
b110 M
b100010 B
b10 G
1)
#900
0)
#910
b1000100001100000100000 !
b1000100001100000100000 /
b1000100001100000100000 Q
b1011 &
b1011 P
1$
b11111111111111111111111111110100 1
b11111111111111111111111111110100 J
b1011 '
b1011 8
1=
b1 @
1%
b1100 ?
b0 ;
b11111111111111111111111111110100 <
b0 G
1)
#920
b10001100000010100000000000000100 !
b10001100000010100000000000000100 /
b10001100000010100000000000000100 Q
b10001100000010100000000000000100 R
0)
#930
bz !
bz /
bz Q
b100 4
b1010 6
b1010 I
b11111111111111111111111111110100 &
b11111111111111111111111111110100 P
0$
b0 K
b1010 L
b11111111111111111111111111110100 '
b11111111111111111111111111110100 8
19
b100000 A
1D
b10 @
0%
0=
b10001100000010100000000000000100 >
b1100 C
b1 G
1)
#940
bx R
0)
#950
bz 1
bz J
b100 7
b100 ;
b11 @
09
0D
b1000 A
1:
1E
b100000 B
b10 G
b0 2
b0 N
b0 0
b0 3
b0 M
1)
#960
0)
#970
bx 1
bx J
bx !
bx /
bx Q
b100 &
b100 P
1$
b100 '
b100 8
1%
b100 @
b0 ;
b100 <
b11 G
1)
#980
b10000010010000000100010 1
b10000010010000000100010 J
b10000010010000000100010 !
b10000010010000000100010 /
b10000010010000000100010 Q
b10000010010000000100010 R
0)
#990
1F
b0 @
1%
b100 G
1)
#1000
0)
#1010
b1100 &
b1100 P
b1100 '
b1100 8
1=
b1 @
b1101 ?
0F
1%
b0 G
1)
#1020
b10100011000100000000000000001 1
b10100011000100000000000000001 J
b10100011000100000000000000001 !
b10100011000100000000000000001 /
b10100011000100000000000000001 Q
b10100011000100000000000000001 R
0)
#1030
bz 1
bz J
bz !
bz /
bz Q
b1 7
b1 4
b10 6
b10 I
b100 &
b100 P
0$
b11 K
b10 L
b100 '
b100 8
b100010 A
0D
b10 @
0%
0=
b10100011000100000000000000001 >
b1101 C
b1 G
b10000010010000000100010 2
b10000010010000000100010 N
1)
#1040
b10000010010000000100010 R
0)
#1050
b100 1
b100 J
b10010 7
b1110 ?
b110 ;
b0 @
b1000 A
b10010 2
b10010 N
b11000 0
b11000 3
b11000 M
0:
0E
b100010 B
b10 G
1)
#1060
0)
#1070
b10000010010000000100010 !
b10000010010000000100010 /
b10000010010000000100010 Q
b1110 &
b1110 P
1$
b110 1
b110 J
b1110 '
b1110 8
1=
b1 @
1%
b1111 ?
b0 ;
b110 <
b1110 C
b0 G
1)
#1080
b1000000000000000000000010000 !
b1000000000000000000000010000 /
b1000000000000000000000010000 Q
b1000000000000000000000010000 R
0)
#1090
bz !
bz /
bz Q
b10000 ?
b10 5
b10000 4
b0 6
b0 I
b110 &
b110 P
0$
b0 K
b0 L
b110 '
b110 8
0D
b0 @
0%
0=
b1000000000000000000000010000 >
b1111 C
b1 G
1)
#1100
b1000100011000000100101 R
0)
#1110
b1000100011000000100101 !
b1000100011000000100101 /
b1000100011000000100101 Q
b10000 &
b10000 P
b10000 '
b10000 8
1$
b0 7
1=
b1 @
1%
b10001 ?
b1000 B
b10000 C
b0 G
b0 2
b0 N
b0 0
b0 3
b0 M
1)
#1120
b10000000000000000001000 !
b10000000000000000001000 /
b10000000000000000001000 Q
b10000000000000000001000 R
0)
#1130
bz !
bz /
bz Q
b1000 4
b0 5
b110 &
b110 P
0$
b10 K
b110 '
b110 8
b10001 ?
b10 @
0%
0=
b10000000000000000001000 >
b10001 C
b1 G
1)
#1140
b1000100011000000100101 R
0)
#1150
b10010 ?
b0 @
b10 G
b10010 0
b10010 3
b10010 M
1)
#1160
0)
#1170
b1000100011000000100101 !
b1000100011000000100101 /
b1000100011000000100101 Q
b10010 &
b10010 P
1$
b0 1
b0 J
b10010 '
b10010 8
1=
b1 @
1%
b10011 ?
b0 <
b10010 C
b0 G
1)
#1180
b10101100000000010000000001000000 !
b10101100000000010000000001000000 /
b10101100000000010000000001000000 Q
b10101100000000010000000001000000 R
0)
#1190
bz !
bz /
bz Q
b1 6
b1 I
1D
b1000000 4
b1 5
b0 &
b0 P
0$
b0 K
b1 L
b0 '
b0 8
b100000 A
b10 @
0%
0=
b10101100000000010000000001000000 >
b10011 C
b1 G
1)
#1200
b110000000000000000000000000000 R
0)
#1210
b1000000 ;
b1000000 7
b11 @
0D
b1000 A
b110 2
b110 N
b0 0
b0 3
b0 M
1E
b100000 B
b10 G
1)
#1220
0)
#1230
b1000000 &
b1000000 P
b110 !
b110 /
b110 Q
1"
1$
b1000000 1
b1000000 J
b1000000 '
b1000000 8
1H
1#
1%
b0 @
b0 ;
b1000000 <
b11 G
1)
#1240
b0 R
b10 .
0)
#1250
b10011 &
b10011 P
b10011 '
b10011 8
b0 !
b0 /
b0 Q
0"
1=
b1 @
b10100 ?
0H
0#
1%
b0 G
1)
#1260
b10101100000000100000000001000001 !
b10101100000000100000000001000001 /
b10101100000000100000000001000001 Q
b10101100000000100000000001000001 R
0)
#1270
bz !
bz /
bz Q
b1000001 7
b1000001 4
b10 6
b10 I
b1000000 &
b1000000 P
0$
b10 L
b1000000 '
b1000000 8
b100000 A
1D
b10 @
0%
0=
b10101100000000100000000001000001 >
b10100 C
b1 G
1)
#1280
b110 R
0)
#1290
b1000001 ;
b11 @
0D
b1000 A
b10010 2
b10010 N
b10 G
1)
#1300
0)
#1310
b1000001 &
b1000001 P
b10010 !
b10010 /
b10010 Q
1"
1$
b1000001 1
b1000001 J
b1000001 '
b1000001 8
1H
1#
1%
b0 @
b0 ;
b1000001 <
b11 G
1)
#1320
b0 R
b11 .
0)
#1330
b10100 &
b10100 P
b10100 '
b10100 8
b0 !
b0 /
b0 Q
0"
1=
b1 @
b10101 ?
0H
0#
1%
b0 G
1)
#1340
b10101100000000110000000001000010 !
b10101100000000110000000001000010 /
b10101100000000110000000001000010 Q
b10101100000000110000000001000010 R
0)
#1350
bz !
bz /
bz Q
b1000010 7
b1000010 4
b11 6
b11 I
b1000001 &
b1000001 P
0$
b11 L
b1000001 '
b1000001 8
b100000 A
1D
b10 @
0%
0=
b10101100000000110000000001000010 >
b10101 C
b1 G
1)
#1360
b10010 R
0)
#1370
b1000010 ;
b11 @
0D
b1000 A
b11000 2
b11000 N
b10 G
1)
#1380
0)
#1390
b1000010 &
b1000010 P
b11000 !
b11000 /
b11000 Q
1"
1$
b1000010 1
b1000010 J
b1000010 '
b1000010 8
1H
1#
1%
b0 @
b0 ;
b1000010 <
b11 G
1)
#1400
b0 R
b100 .
0)
#1410
b10101 &
b10101 P
b10101 '
b10101 8
b0 !
b0 /
b0 Q
0"
1=
b1 @
b10110 ?
0H
0#
1%
b0 G
1)
#1420
b10101100000001000000000001000011 !
b10101100000001000000000001000011 /
b10101100000001000000000001000011 Q
b10101100000001000000000001000011 R
0)
#1430
bz !
bz /
bz Q
b1000011 7
b1000011 4
b100 6
b100 I
b1000010 &
b1000010 P
0$
b100 L
b1000010 '
b1000010 8
b100000 A
1D
b10 @
0%
0=
b10101100000001000000000001000011 >
b10110 C
b1 G
1)
#1440
b11000 R
0)
#1450
b1000011 ;
b11 @
0D
b1000 A
b1100 2
b1100 N
b10 G
1)
#1460
0)
#1470
b1000011 &
b1000011 P
b1100 !
b1100 /
b1100 Q
1"
1$
b1000011 1
b1000011 J
b1000011 '
b1000011 8
1H
1#
1%
b0 @
b0 ;
b1000011 <
b11 G
1)
#1480
b0 R
b101 .
0)
#1490
b10110 &
b10110 P
b10110 '
b10110 8
b0 !
b0 /
b0 Q
0"
1=
b1 @
b10111 ?
0H
0#
1%
b0 G
1)
#1500
b10101100000001010000000001000100 !
b10101100000001010000000001000100 /
b10101100000001010000000001000100 Q
b10101100000001010000000001000100 R
0)
#1510
bz !
bz /
bz Q
b1000100 7
b1000100 4
b101 6
b101 I
b1000011 &
b1000011 P
0$
b101 L
b1000011 '
b1000011 8
b100000 A
1D
b10 @
0%
0=
b10101100000001010000000001000100 >
b10111 C
b1 G
1)
#1520
b1100 R
0)
#1530
b1000100 ;
b11 @
0D
b1000 A
b10 2
b10 N
b10 G
1)
#1540
0)
#1550
b1000100 &
b1000100 P
b10 !
b10 /
b10 Q
1"
1$
b1000100 1
b1000100 J
b1000100 '
b1000100 8
1H
1#
1%
b0 @
b0 ;
b1000100 <
b11 G
1)
#1560
b0 R
b110 .
0)
#1570
b10111 &
b10111 P
b10111 '
b10111 8
b0 !
b0 /
b0 Q
0"
1=
b1 @
b11000 ?
0H
0#
1%
b0 G
1)
#1580
b10101100000001100000000001000101 !
b10101100000001100000000001000101 /
b10101100000001100000000001000101 Q
b10101100000001100000000001000101 R
0)
#1590
bz !
bz /
bz Q
b1000101 7
b1000101 4
b110 6
b110 I
b1000100 &
b1000100 P
0$
b110 L
b1000100 '
b1000100 8
b100000 A
1D
b10 @
0%
0=
b10101100000001100000000001000101 >
b11000 C
b1 G
1)
#1600
b10 R
0)
#1610
b1000101 ;
b11 @
0D
b1000 A
b10110 2
b10110 N
b10 G
1)
#1620
0)
#1630
b1000101 &
b1000101 P
b10110 !
b10110 /
b10110 Q
1"
1$
b1000101 1
b1000101 J
b1000101 '
b1000101 8
1H
1#
1%
b0 @
b0 ;
b1000101 <
b11 G
1)
